markovlogging/__init__.py
markovlogging/example.py
markovlogging-0.0.2.dist-info/METADATA
markovlogging-0.0.2.dist-info/WHEEL
markovlogging-0.0.2.dist-info/licenses/LICENSE
markovlogging-0.0.2.dist-info/RECORD
